{
    "success": true,
    "data": {
        "currentchap": {
            "ChapNumber": 19,
            "StoryID": "64a9328d0631ac36f4d6e80f",
            "StoryName": "Dị Thế Tà Quân",
            "ChapTitle": "chapter 19",
            "ChapContent": "<img src='https://img02.vnmanga.top/bbdata/5db30a1d0631ac1c18cd1e76/02_u62c80g4eqidvs.jpg' alt='Dị Thế Tà Quân chapter 19 - Upload bởi truyensieuhay.com'/><br/><img src='https://img02.vnmanga.top/bbdata/5db30a1d0631ac1c18cd1e76/03_u62c8pb54sr0p0chfwa.jpg' alt='Dị Thế Tà Quân chapter 19 - Upload bởi truyensieuhay.com'/><br/><img src='https://img02.vnmanga.top/bbdata/5db30a1d0631ac1c18cd1e76/04_u62c8iwjn3yspgc.jpg' alt='Dị Thế Tà Quân chapter 19 - Upload bởi truyensieuhay.com'/><br/><img src='https://img02.vnmanga.top/bbdata/5db30a1d0631ac1c18cd1e76/05_u62c88vdlla5jpb1y.jpg' alt='Dị Thế Tà Quân chapter 19 - Upload bởi truyensieuhay.com'/><br/><img src='https://img02.vnmanga.top/bbdata/5db30a1d0631ac1c18cd1e76/06_u62c82bc2nygxn4ns.jpg' alt='Dị Thế Tà Quân chapter 19 - Upload bởi truyensieuhay.com'/><br/><img src='https://img02.vnmanga.top/bbdata/5db30a1d0631ac1c18cd1e76/07_u62c8dm2qfzm2rndyh17.jpg' alt='Dị Thế Tà Quân chapter 19 - Upload bởi truyensieuhay.com'/><br/><img src='https://img02.vnmanga.top/bbdata/5db30a1d0631ac1c18cd1e76/08_u62c8qvt1arl8tmdo.jpg' alt='Dị Thế Tà Quân chapter 19 - Upload bởi truyensieuhay.com'/><br/><img src='https://img02.vnmanga.top/bbdata/5db30a1d0631ac1c18cd1e76/09_u62c8lz2nia3seabky.jpg' alt='Dị Thế Tà Quân chapter 19 - Upload bởi truyensieuhay.com'/><br/><img src='https://img02.vnmanga.top/bbdata/5db30a1d0631ac1c18cd1e76/010_u62c8q49f7rvya8oz3q7.jpg' alt='Dị Thế Tà Quân chapter 19 - Upload bởi truyensieuhay.com'/><br/><img src='https://img02.vnmanga.top/bbdata/5db30a1d0631ac1c18cd1e76/00_u62c8ptnvmibeq7ouvsw.jpg' alt='Dị Thế Tà Quân chapter 19 - Upload bởi truyensieuhay.com'/><br/>",
            "ChapNameK": "di-the-ta-quan-chapter-19",
            "ChapStatus": 0,
            "ChapTags": "https://manhuavn.top/doc-truyen/di-the-ta-quan-chapter-19.html",
            "ChapPCount": 1,
            "ChapPostDate": "2023-07-14T21:29:15.3641402Z",
            "ChapLinkDown": "",
            "ChapThongBao": "",
            "ChapUserPost": "-1",
            "ChapContentVideo": null,
            "ChapContentVideoTimeActive": "0001-01-01T00:00:00Z",
            "ChapPrice": 2,
            "TotalBuy": 0,
            "TotalThanks": 0,
            "ChapterContent2": null,
            "ChapterBuyByCongHien": 0,
            "Id": "64b15bbb0631ac04943469b8",
            "MongoId": "64b15bbb0631ac04943469b8"
        },
        "nextchap": "64b15bc20631ac04943469d6",
        "prevchap": "64b15bb40631ac0494346996",
        "numberlike": 0,
        "isthanks": false,
        "hasbuy": false,
        "themkn": false
    }
}