{
    "success": true,
    "data": {
        "currentchap": {
            "ChapNumber": 45,
            "StoryID": "64a9328d0631ac36f4d6e80f",
            "StoryName": "Dị Thế Tà Quân",
            "ChapTitle": "chapter 45",
            "ChapContent": "<img src='https://img02.vnmanga.top/bbdata/5e3d2fd70631ac39e8416362/0_cro6x1tcuem2rdf9ds3nb.jpg' alt='Dị Thế Tà Quân chapter 45 - Upload bởi truyensieuhay.com'/><br/><img src='https://img02.vnmanga.top/bbdata/5e3d2fd70631ac39e8416362/1_cro6x1tcs5waqlk0zozju.jpg' alt='Dị Thế Tà Quân chapter 45 - Upload bởi truyensieuhay.com'/><br/><img src='https://img02.vnmanga.top/bbdata/5e3d2fd70631ac39e8416362/2_cro6x1tctr3ices6b8vj9s.jpg' alt='Dị Thế Tà Quân chapter 45 - Upload bởi truyensieuhay.com'/><br/><img src='https://img02.vnmanga.top/bbdata/5e3d2fd70631ac39e8416362/3_cro6x1tcuh2mc10zmi9.jpg' alt='Dị Thế Tà Quân chapter 45 - Upload bởi truyensieuhay.com'/><br/><img src='https://img02.vnmanga.top/bbdata/5e3d2fd70631ac39e8416362/4_cro6x1tctgpqv3jkujul.jpg' alt='Dị Thế Tà Quân chapter 45 - Upload bởi truyensieuhay.com'/><br/><img src='https://img02.vnmanga.top/bbdata/5e3d2fd70631ac39e8416362/5_cro6x1tcsei9xyynipf7wsy.jpg' alt='Dị Thế Tà Quân chapter 45 - Upload bởi truyensieuhay.com'/><br/><img src='https://img02.vnmanga.top/bbdata/5e3d2fd70631ac39e8416362/6_cro6x1tcu1erdsline05sui.jpg' alt='Dị Thế Tà Quân chapter 45 - Upload bởi truyensieuhay.com'/><br/><img src='https://img02.vnmanga.top/bbdata/5e3d2fd70631ac39e8416362/7_cro6x1tct8w4fmraaq90s.jpg' alt='Dị Thế Tà Quân chapter 45 - Upload bởi truyensieuhay.com'/><br/><img src='https://img02.vnmanga.top/bbdata/5e3d2fd70631ac39e8416362/8_cro6x1tcs8pf6ftq0ngv.jpg' alt='Dị Thế Tà Quân chapter 45 - Upload bởi truyensieuhay.com'/><br/><img src='https://img02.vnmanga.top/bbdata/5e3d2fd70631ac39e8416362/9_cro6x1tctj6bdsrsgm6k7.jpg' alt='Dị Thế Tà Quân chapter 45 - Upload bởi truyensieuhay.com'/><br/><img src='https://img02.vnmanga.top/bbdata/5e3d2fd70631ac39e8416362/10_cro6x1tcsmtk2ye9fed3cu.jpg' alt='Dị Thế Tà Quân chapter 45 - Upload bởi truyensieuhay.com'/><br/><img src='https://img02.vnmanga.top/bbdata/5e3d2fd70631ac39e8416362/11_cro6x1tcs9bxv8md8v64o.jpg' alt='Dị Thế Tà Quân chapter 45 - Upload bởi truyensieuhay.com'/><br/><img src='https://img02.vnmanga.top/bbdata/5e3d2fd70631ac39e8416362/12_cro6x1tcvxgrhkhomx5bl82r8.jpg' alt='Dị Thế Tà Quân chapter 45 - Upload bởi truyensieuhay.com'/><br/>",
            "ChapNameK": "di-the-ta-quan-chapter-45",
            "ChapStatus": 0,
            "ChapTags": "https://manhuavn.top/doc-truyen/di-the-ta-quan-chapter-45.html",
            "ChapPCount": 2,
            "ChapPostDate": "2023-07-14T21:33:29.6241089Z",
            "ChapLinkDown": "",
            "ChapThongBao": "",
            "ChapUserPost": "-1",
            "ChapContentVideo": null,
            "ChapContentVideoTimeActive": "0001-01-01T00:00:00Z",
            "ChapPrice": 2,
            "TotalBuy": 0,
            "TotalThanks": 0,
            "ChapterContent2": null,
            "ChapterBuyByCongHien": 0,
            "Id": "64b15cb90631ac0494346dc9",
            "MongoId": "64b15cb90631ac0494346dc9"
        },
        "nextchap": "64b15cc20631ac0494346de6",
        "prevchap": "64b15cb40631ac0494346db5",
        "numberlike": 0,
        "isthanks": false,
        "hasbuy": false,
        "themkn": false
    }
}